bsicons/LICENSE
bsicons/README.md
bsicons/__init__.pyi
bsicons/__init__.pyx
bsicons/py.typed
bsicons/__pyinstaller/__init__.py
bsicons/__pyinstaller/hook-bsicons.py
bsicons/icons/0-circle-fill.svg
bsicons/icons/0-circle.svg
bsicons/icons/0-square-fill.svg
bsicons/icons/0-square.svg
bsicons/icons/1-circle-fill.svg
bsicons/icons/1-circle.svg
bsicons/icons/1-square-fill.svg
bsicons/icons/1-square.svg
bsicons/icons/123.svg
bsicons/icons/2-circle-fill.svg
bsicons/icons/2-circle.svg
bsicons/icons/2-square-fill.svg
bsicons/icons/2-square.svg
bsicons/icons/3-circle-fill.svg
bsicons/icons/3-circle.svg
bsicons/icons/3-square-fill.svg
bsicons/icons/3-square.svg
bsicons/icons/4-circle-fill.svg
bsicons/icons/4-circle.svg
bsicons/icons/4-square-fill.svg
bsicons/icons/4-square.svg
bsicons/icons/5-circle-fill.svg
bsicons/icons/5-circle.svg
bsicons/icons/5-square-fill.svg
bsicons/icons/5-square.svg
bsicons/icons/6-circle-fill.svg
bsicons/icons/6-circle.svg
bsicons/icons/6-square-fill.svg
bsicons/icons/6-square.svg
bsicons/icons/7-circle-fill.svg
bsicons/icons/7-circle.svg
bsicons/icons/7-square-fill.svg
bsicons/icons/7-square.svg
bsicons/icons/8-circle-fill.svg
bsicons/icons/8-circle.svg
bsicons/icons/8-square-fill.svg
bsicons/icons/8-square.svg
bsicons/icons/9-circle-fill.svg
bsicons/icons/9-circle.svg
bsicons/icons/9-square-fill.svg
bsicons/icons/9-square.svg
bsicons/icons/activity.svg
bsicons/icons/airplane-engines-fill.svg
bsicons/icons/airplane-engines.svg
bsicons/icons/airplane-fill.svg
bsicons/icons/airplane.svg
bsicons/icons/alarm-fill.svg
bsicons/icons/alarm.svg
bsicons/icons/alexa.svg
bsicons/icons/align-bottom.svg
bsicons/icons/align-center.svg
bsicons/icons/align-end.svg
bsicons/icons/align-middle.svg
bsicons/icons/align-start.svg
bsicons/icons/align-top.svg
bsicons/icons/alipay.svg
bsicons/icons/alphabet-uppercase.svg
bsicons/icons/alphabet.svg
bsicons/icons/alt.svg
bsicons/icons/amazon.svg
bsicons/icons/amd.svg
bsicons/icons/android.svg
bsicons/icons/android2.svg
bsicons-25.1.dist-info/LICENSE
bsicons-25.1.dist-info/METADATA
bsicons-25.1.dist-info/WHEEL
bsicons-25.1.dist-info/entry_points.txt
bsicons-25.1.dist-info/top_level.txt
bsicons-25.1.dist-info/RECORD
